rbot/__init__.py
rbot/colorExtractor.py
rbot/dataCollector.py
rbot/rbot.py
rbot/trainer.py
rbot/version.py
rbobjecttracking-3.2.0.dist-info/METADATA
rbobjecttracking-3.2.0.dist-info/WHEEL
rbobjecttracking-3.2.0.dist-info/top_level.txt
rbobjecttracking-3.2.0.dist-info/RECORD
