Metadata-Version: 2.4
Name: rbobjecttracking
Version: 3.2.0
Summary: A python library for single-object tracking.
Author: Samarth Javagal
Author-email: samarthjavagal@gmail.com
Classifier: Programming Language :: Python :: 3
Classifier: License :: OSI Approved :: MIT License
Classifier: Operating System :: OS Independent
Requires-Python: >=3.6
Requires-Dist: numpy
Requires-Dist: opencv-python
Requires-Dist: customtkinter
Requires-Dist: cvzone
Requires-Dist: rembg
Requires-Dist: scikit-learn
Requires-Dist: scikit-image
Requires-Dist: joblib
Dynamic: author
Dynamic: author-email
Dynamic: classifier
Dynamic: description
Dynamic: description-content-type
Dynamic: requires-dist
Dynamic: requires-python
Dynamic: summary
